setup.py
CydraGitHTTP.egg-info/PKG-INFO
CydraGitHTTP.egg-info/SOURCES.txt
CydraGitHTTP.egg-info/dependency_links.txt
CydraGitHTTP.egg-info/entry_points.txt
CydraGitHTTP.egg-info/namespace_packages.txt
CydraGitHTTP.egg-info/requires.txt
CydraGitHTTP.egg-info/top_level.txt
cydraplugins/__init__.py
cydraplugins/githttp/__init__.py
cydraplugins/githttp/git_http_backend.py
cydraplugins/githttp/gittornado_integration.py
cydraplugins/githttp/subprocessio.py