Metadata-Version: 1.0
Name: CydraGitHTTP
Version: 0.1
Summary: Cydra plugin for git http serving
Home-page: http://www.cydra.org
Author: Manuel Stocker, D. Dotsenko
Author-email: mensi@vis.ethz.ch, dotsa@hotmail.com
License: GPL
Keywords: cydra git http
Platform: UNKNOWN
